edgegrid_python-2.0.3-py3.13-nspkg.pth
akamai/edgegrid/__init__.py
akamai/edgegrid/edgegrid.py
akamai/edgegrid/edgerc.py
akamai/edgegrid/test/__init__.py
akamai/edgegrid/test/conftest.py
akamai/edgegrid/test/edgerc_that_doesnt_parse
akamai/edgegrid/test/sample_edgerc
akamai/edgegrid/test/sample_file.txt
akamai/edgegrid/test/test_edgegrid.py
akamai/edgegrid/test/testcases.json
akamai/edgegrid/test/testdata.json
edgegrid_python-2.0.3.dist-info/licenses/LICENSE
edgegrid_python-2.0.3.dist-info/METADATA
edgegrid_python-2.0.3.dist-info/WHEEL
edgegrid_python-2.0.3.dist-info/namespace_packages.txt
edgegrid_python-2.0.3.dist-info/top_level.txt
edgegrid_python-2.0.3.dist-info/RECORD
