Metadata-Version: 2.4
Name: edgegrid-python
Version: 2.0.3
Summary: {OPEN} client authentication protocol for python-requests
Home-page: https://github.com/akamai/AkamaiOPEN-edgegrid-python
License: Apache 2.0
Classifier: License :: OSI Approved :: Apache Software License
Classifier: Programming Language :: Python :: 3
Requires-Python: >=3.10
License-File: LICENSE
Requires-Dist: requests>=2.24.0
Requires-Dist: requests_toolbelt>=0.9.1
Provides-Extra: dev
Requires-Dist: pylint>=2.7.0; extra == "dev"
Requires-Dist: pytest>=6.1.0; extra == "dev"
Requires-Dist: pytest-cov>=2.12.1; extra == "dev"
Dynamic: classifier
Dynamic: description
Dynamic: description-content-type
Dynamic: home-page
Dynamic: license
Dynamic: license-file
Dynamic: provides-extra
Dynamic: requires-dist
Dynamic: requires-python
Dynamic: summary
